digitaldna/__init__.py
digitaldna/lcs.py
digitaldna/sequence_plots.py
digitaldna/twitter_sequencer.py
digitaldna/verbosity.py
digitaldna/tests/__init__.py
digitaldna/tests/test_lcs.py
digitaldna/tests/test_sequence_plots.py
digitaldna/tests/test_twitter_sequencer.py
digitaldna-0.0.5.dist-info/LICENSE
digitaldna-0.0.5.dist-info/METADATA
digitaldna-0.0.5.dist-info/WHEEL
digitaldna-0.0.5.dist-info/top_level.txt
digitaldna-0.0.5.dist-info/RECORD
